lazzaro/__init__.py
lazzaro/cli/__init__.py
lazzaro/cli/main.py
lazzaro/core/__init__.py
lazzaro/core/buffer_graph.py
lazzaro/core/interfaces.py
lazzaro/core/memory_shard.py
lazzaro/core/memory_system.py
lazzaro/core/profile.py
lazzaro/core/providers.py
lazzaro/core/query_cache.py
lazzaro/core/vector_store.py
lazzaro/dashboard/__init__.py
lazzaro/dashboard/api.py
lazzaro/dashboard/templates/index.html
lazzaro/integrations/__init__.py
lazzaro/integrations/adk_integration.py
lazzaro/integrations/autogen_integration.py
lazzaro/integrations/langchain_integration.py
lazzaro/integrations/langgraph_integration.py
lazzaro/models/__init__.py
lazzaro/models/graph.py
lazzaro-0.2.5.2.dist-info/METADATA
lazzaro-0.2.5.2.dist-info/WHEEL
lazzaro-0.2.5.2.dist-info/entry_points.txt
lazzaro-0.2.5.2.dist-info/top_level.txt
lazzaro-0.2.5.2.dist-info/RECORD
