Metadata-Version: 2.4
Name: lazzaro
Version: 0.2.5.2
Summary: A scalable memory system for AI agents using graph-based sharding and hierarchical clustering.
Author-email: Tobi Balogun <tobitobitobiwhy@gmail.com>
License: MIT
Project-URL: Homepage, https://github.com/thelaycon/lazzaro
Requires-Python: >=3.8
Requires-Dist: openai
Requires-Dist: numpy
Requires-Dist: networkx
Requires-Dist: matplotlib
Requires-Dist: plotly
Requires-Dist: fastapi
Requires-Dist: uvicorn
Requires-Dist: jinja2
Requires-Dist: lancedb
Requires-Dist: pyarrow
